{
    "pos": {
        "x": 0.0,
        "y": 0.5,
        "z": -3.0
    },
    "vertices": [{
        "x": -3.0,
        "y": 0.0,
        "z": 0.0
    }, {
        "x": 0.0,
        "y": 0.0,
        "z": 3.0
    }, {
        "x": 3.0,
        "y": 0.0,
        "z": 0.0
    }, {
        "x": 0.0,
        "y": 0.0,
        "z": -3.0
    }, {
        "x": 0.0,
        "y": 3.0,
        "z": 0.0
    }],
    "faces": [
        [0, 2, 1],
        [0, 3, 2],
        [4, 0, 1],
        [4, 1, 2],
        [4, 2, 3],
        [4, 3, 0]
    ],
    "material": {
        "ambient_constant": {
            "r": 0,
            "g": 0,
            "b": 255,
            "a": 255
        },
        "diffuse_constant": 50.0,
        "specular_constant": 20.0,
        "shine": 7.0
    }
}